gtape_prologix_drivers/__init__.py
gtape_prologix_drivers/adapter.py
gtape_prologix_drivers/instruments/__init__.py
gtape_prologix_drivers/instruments/agilent_e3631a.py
gtape_prologix_drivers/instruments/hp33120a.py
gtape_prologix_drivers/instruments/hp34401a.py
gtape_prologix_drivers/instruments/plz164w.py
gtape_prologix_drivers/instruments/tds3000.py
gtape_prologix_drivers/instruments/tds460a.py
gtape_prologix_drivers-0.2.0.dist-info/METADATA
gtape_prologix_drivers-0.2.0.dist-info/WHEEL
gtape_prologix_drivers-0.2.0.dist-info/licenses/LICENSE
gtape_prologix_drivers-0.2.0.dist-info/RECORD
