Metadata-Version: 2.4
Name: gtape-prologix-drivers
Version: 0.2.0
Summary: Python drivers for lab instruments via Prologix GPIB-USB controller
Project-URL: Homepage, https://github.com/cognitohazard/gtape-prologix-drivers
Project-URL: Documentation, https://github.com/cognitohazard/gtape-prologix-drivers#readme
Project-URL: Repository, https://github.com/cognitohazard/gtape-prologix-drivers
Project-URL: Issues, https://github.com/cognitohazard/gtape-prologix-drivers/issues
Author-email: Cognitohazard <me@cog.icu>
License-Expression: MIT
License-File: LICENSE
Keywords: e3631a,gpib,hp33120a,hp34401a,lab-instruments,plz164w,prologix,scpi,tds3000,tds460a,test-equipment
Classifier: Development Status :: 4 - Beta
Classifier: Intended Audience :: Science/Research
Classifier: License :: OSI Approved :: MIT License
Classifier: Programming Language :: Python :: 3.10
Classifier: Programming Language :: Python :: 3.11
Classifier: Programming Language :: Python :: 3.12
Classifier: Programming Language :: Python :: 3.13
Classifier: Topic :: Scientific/Engineering
Classifier: Topic :: Scientific/Engineering :: Interface Engine/Protocol Translator
Requires-Python: >=3.10
Requires-Dist: pyserial>=3.5
Provides-Extra: awg
Requires-Dist: numpy>=1.24; extra == 'awg'
Provides-Extra: dev
Requires-Dist: pytest-cov; extra == 'dev'
Requires-Dist: pytest>=7.0; extra == 'dev'
